moviemaker/__main__.py
moviemaker/moviemaker.py
moviemaker/moviemaker_ui.py
moviemaker/resource_rc.py
moviemaker/ui/moviemaker_mw.ui
moviemaker/ui/resource.qrc
moviemaker/ui/resources/icons8-bobina-40.png
moviemaker/ui/resources/icons8-ok-30.png
moviemaker/ui/resources/icons8-opened-folder-30.png
moviemaker/ui/resources/icons8-start-30.png
moviemaker-0.0.1.dist-info/METADATA
moviemaker-0.0.1.dist-info/WHEEL
moviemaker-0.0.1.dist-info/license_files/LICENSE
moviemaker-0.0.1.dist-info/RECORD
