Metadata-Version: 2.1
Name: moviemaker
Version: 0.0.1
Summary: An ultra simple image to movie converter.
Project-URL: Homepage, https://github.com/abulgher/moviemaker
Author-email: Antonio Bulgheroni <antonio.bulgheroni@gmail.com>
License: MIT License
Classifier: License :: OSI Approved :: MIT License
Classifier: Operating System :: OS Independent
Classifier: Programming Language :: Python :: 3
Requires-Python: >=3.9.7
Requires-Dist: moviepy>=1.0.3
Requires-Dist: pillow>=9.1.1
Requires-Dist: pyqt5>=5.9.2
Requires-Dist: tifffile>=2022.5.4
